AUTHORS
ChangeLog
README.md
setup.cfg
setup.py
gpg_forward/__init__.py
gpg_forward.egg-info/PKG-INFO
gpg_forward.egg-info/SOURCES.txt
gpg_forward.egg-info/dependency_links.txt
gpg_forward.egg-info/entry_points.txt
gpg_forward.egg-info/not-zip-safe
gpg_forward.egg-info/pbr.json
gpg_forward.egg-info/top_level.txt