Metadata-Version: 1.2
Name: gpg-forward
Version: 0.0.0
Summary: Forward GPG agent socket to remote host over SSH
Home-page: https://github.com/psliwka/gpg-forward
Author: Piotr Śliwka
Author-email: contact@psliwka.info
License: MIT
Platform: UNKNOWN
Requires-Python: >3.6
